customerrors/__init__.py
customerrors/customerrors.py
customerrors/pgame.py
customerrors/pgame_test.py
customerrors/tests/__init__.py
customerrs/__init__.py
customerrs/customerrors.py
customerrs/pgame.py
customerrs/pgame_test.py
customerrs/tests/__init__.py
main/__init__.py
main/customerrors.py
main/pgame.py
main/pgame_test.py
main/tests/__init__.py
main/tests/customerrors.py
main/tests/pgame.py
main/tests/pgame_test.py
tests/__init__.py
tests/customerrors.py
tests/pgame.py
tests/pgame_test.py
customerrors-0.0.6.dist-info/METADATA
customerrors-0.0.6.dist-info/WHEEL
customerrors-0.0.6.dist-info/top_level.txt
customerrors-0.0.6.dist-info/RECORD
