Metadata-Version: 2.1
Name: customerrors
Version: 0.0.6
Summary: A pypi test.
Home-page: UNKNOWN
Author: Splatboy Dev
Author-email: splatboy20081@gmail.com
License: BSD
Keywords: example documentation tutorial
Platform: UNKNOWN
Classifier: Development Status :: 3 - Alpha
Classifier: License :: OSI Approved :: BSD License
